.gitignore
LICENSE
README.md
setup.py
.github/workflows/python-package.yml
docs/Makefile
docs/conf.py
docs/index.rst
docs/make.bat
docs/reference.rst
pipcs/__init__.py
pipcs/pipcs.py
pipcs.egg-info/PKG-INFO
pipcs.egg-info/SOURCES.txt
pipcs.egg-info/dependency_links.txt
pipcs.egg-info/top_level.txt
tests/__init__.py
tests/test_config.py