Metadata-Version: 2.1
Name: pipcs
Version: 1.3.3
Summary: pipcs is python configuration system
Home-page: https://github.com/goktug97/pipcs
Author: Göktuğ Karakaşlı
Author-email: karakasligk@gmail.com
License: MIT
Platform: UNKNOWN
Classifier: Programming Language :: Python :: 3
Classifier: License :: OSI Approved :: MIT License
Requires-Python: >=3.7
